[
    {
        "email": "test@mail.ru",
        "password": "test123",
        "name": "Andrew Mukha",
        "position": "Администратор",
        "employeesData": {
            "salePhones": [],
            "canUseAdminPanel": true,
            "canAddPhones": true,
            "canEditPhones": true,
            "canShowListOfPhones": true,
            "canChangeUsers": true,
            "canShowOrders": true,
            "canShowDataAboutSaler": true,
            "canShowSalerData": true,
            "canSold": true,
            "canShowSolds": true
        }
    },
    {
        "email": "test1@mail.ru",
        "password": "test123",
        "name": "Бортновская Валерия",
        "position": "Администратор",
        "employeesData": {
            "salePhones": [],
            "canUseAdminPanel": true,
            "canAddPhones": true,
            "canEditPhones": true,
            "canShowListOfPhones": true,
            "canChangeUsers": true,
            "canShowOrders": true,
            "canShowDataAboutSaler": true,
            "canShowSalerData": true,
            "canSold": true,
            "canShowSolds": true
        }
    },
    {
        "email": "admin@mail.ru",
        "password": "admin",
        "name": "Admin",
        "position": "Администратор",
        "employeesData": {
            "salePhones": [],
            "canUseAdminPanel": true,
            "canAddPhones": true,
            "canEditPhones": true,
            "canShowListOfPhones": true,
            "canChangeUsers": true,
            "canShowOrders": true,
            "canShowDataAboutSaler": true,
            "canShowSalerData": true,
            "canSold": true,
            "canShowSolds": true
        }
    },
    {
        "email": "saler@mail.ru",
        "password": "saler",
        "name": "Продавец",
        "position": "Продавец",
        "employeesData": {
            "salePhones": [
                {
                    "phoneName": "Xiaomi Redmi Note 11",
                    "clientEmail": "admin@mail.ru",
                    "employeeEmail": "saler@mail.ru",
                    "dateTime": "2022-05-05T20:10:13.1839315+03:00",
                    "linkToHtml": "..\\..\\..\\SaleReports\\Xiaomi Redmi Note 11 05.05.2022-183.html",
                    "price": 825
                },
                {
                    "phoneName": " Realme 8i",
                    "clientEmail": "test1@mail.ru",
                    "employeeEmail": "saler@mail.ru",
                    "dateTime": "2022-05-05T20:10:30.5058933+03:00",
                    "linkToHtml": "..\\..\\..\\SaleReports\\ Realme 8i 05.05.2022-505.html",
                    "price": 805
                }
            ],
            "canUseAdminPanel": true,
            "canAddPhones": false,
            "canEditPhones": false,
            "canShowListOfPhones": false,
            "canChangeUsers": false,
            "canShowOrders": true,
            "canShowDataAboutSaler": true,
            "canShowSalerData": false,
            "canSold": true,
            "canShowSolds": false
        }
    },
    {
        "email": "manager@mail.ru",
        "password": "manager",
        "name": "Manager",
        "position": "Менеджер",
        "employeesData": {
            "salePhones": [],
            "canUseAdminPanel": true,
            "canAddPhones": false,
            "canEditPhones": false,
            "canShowListOfPhones": true,
            "canChangeUsers": false,
            "canShowOrders": false,
            "canShowDataAboutSaler": false,
            "canShowSalerData": false,
            "canSold": false,
            "canShowSolds": true
        }
    }
]